weblogo/__init__.py
weblogo/_cgi.py
weblogo/_cli.py
weblogo/_transformseq.py
weblogo/color.py
weblogo/colorscheme.py
weblogo/data.py
weblogo/logo.py
weblogo/logo_formatter.py
weblogo/logomath.py
weblogo/matrix.py
weblogo/seq.py
weblogo/template.eps
weblogo/transform.py
weblogo/data/blosum100.mat
weblogo/data/blosum35.mat
weblogo/data/blosum40.mat
weblogo/data/blosum45.mat
weblogo/data/blosum50.mat
weblogo/data/blosum62.mat
weblogo/data/blosum80.mat
weblogo/data/dbxref.txt
weblogo/data/dist20_comp.mat
weblogo/data/pam120.mat
weblogo/data/pam250.mat
weblogo/htdocs/create.cgi
weblogo/htdocs/create_html_template.html
weblogo/htdocs/examples.html
weblogo/htdocs/favicon.ico
weblogo/htdocs/index.html
weblogo/htdocs/logo.css
weblogo/htdocs/manual.html
weblogo/htdocs/test.html
weblogo/htdocs/weblogo_changelog.txt
weblogo/htdocs/examples/build_examples.sh
weblogo/htdocs/examples/cap_dna.fa
weblogo/htdocs/examples/cap_dna.png
weblogo/htdocs/examples/cap_hth.fa
weblogo/htdocs/examples/cap_hth.png
weblogo/htdocs/examples/ecoli10.fa
weblogo/htdocs/examples/ecoli10.png
weblogo/htdocs/examples/exon-intron.fa
weblogo/htdocs/examples/exon-intron.png
weblogo/htdocs/examples/globins.fa
weblogo/htdocs/examples/globins.png
weblogo/htdocs/examples/hth.fa
weblogo/htdocs/examples/hth.png
weblogo/htdocs/examples/intron-exon.fa
weblogo/htdocs/examples/intron-exon.png
weblogo/htdocs/examples/lexA.fa
weblogo/htdocs/examples/lexA.png
weblogo/htdocs/examples/prenyl.fa
weblogo/htdocs/img/example.png
weblogo/htdocs/img/feed-icon-16x16.png
weblogo/htdocs/img/weblogo-fig1.png
weblogo/htdocs/img/weblogo_create.png
weblogo/seq_io/__init__.py
weblogo/seq_io/array_io.py
weblogo/seq_io/clustal_io.py
weblogo/seq_io/fasta_io.py
weblogo/seq_io/genbank_io.py
weblogo/seq_io/intelligenetics_io.py
weblogo/seq_io/msf_io.py
weblogo/seq_io/nbrf_io.py
weblogo/seq_io/nexus_io.py
weblogo/seq_io/null_io.py
weblogo/seq_io/phylip_io.py
weblogo/seq_io/plain_io.py
weblogo/seq_io/stockholm_io.py
weblogo/seq_io/table_io.py
weblogo-3.7.12.dist-info/LICENSE.txt
weblogo-3.7.12.dist-info/METADATA
weblogo-3.7.12.dist-info/WHEEL
weblogo-3.7.12.dist-info/entry_points.txt
weblogo-3.7.12.dist-info/top_level.txt
weblogo-3.7.12.dist-info/RECORD
